jss/__init__.py
jss/abstract.py
jss/auth.py
jss/casper.py
jss/curl_adapter.py
jss/distribution_point.py
jss/distribution_points.py
jss/exceptions.py
jss/jamf_software_server.py
jss/jss_prefs.py
jss/jssobject.py
jss/jssobjectlist.py
jss/jssobjects.py
jss/misc_endpoints.py
jss/misc_uapi_endpoints.py
jss/nsurlsession_adapter.py
jss/pretty_element.py
jss/queryset.py
jss/tlsadapter.py
jss/tools.py
jss/uapiobject.py
jss/uapiobjects.py
jss/upload_endpoints.py
jss/contrib/FoundationPlist.py
jss/contrib/__init__.py
jss/contrib/gurl.py
jss/contrib/mount_shares_better.py
python_jss-2.1.0.dist-info/LICENSE.txt
python_jss-2.1.0.dist-info/METADATA
python_jss-2.1.0.dist-info/WHEEL
python_jss-2.1.0.dist-info/top_level.txt
python_jss-2.1.0.dist-info/RECORD
