Metadata-Version: 2.1
Name: python-jss
Version: 2.1.0
Summary: Python wrapper for JSS API.
Home-page: https://github.com/JSSImporter/python-jss/
Author: Shea G. Craig
License: GPLv3
Platform: UNKNOWN
Classifier: Development Status :: 5 - Production/Stable
Classifier: License :: OSI Approved :: GNU General Public License v3 (GPLv3)
Requires-Dist: requests (>=2.24.0)
Provides-Extra: rest
Requires-Dist: Sphinx (>=3.1.2) ; extra == 'rest'
Requires-Dist: docutils (>=0.16) ; extra == 'rest'
